{"type":"PR","pr":{"number":85,"head":"fc82fc04c0946adaa2d6f87f9ebe13e271c181fa"},"user":"kikko","status":"pending_publish","branch":"cms/index","collection":"pages","title":"Hobbes","description":"Sed ut perspiciatis unde omnis iste natus error sit voluptatem accusantium doloremque laudantium, luptatem quia volupt inventore totam rem aperiam, eaque ipsa quae ab illo inventore veritatis et quasi architecto beatae vitae dicta sunt explicabo. Nemo enim ipsam voluptatem quia voluptas sit aspernatur aut odit aut fugit, sed quia consequuntur magni dolores eos qui ratione voluptatem sequi nesciunt.\n \n\t\tPerspiciatis unde omnis iste natus error sit voluptatem accusantium doloremque laudantium, totam rem aperiam, eaque ipsa quae ab illo inventore veritatis et quasi architecto beatae vitae dicta sunt explicabo. Nemo enim ipsam voluptatem quia voluptas sit aspernatur aut odit aut fugit, sed quia consequuntur magni dolores eos qui ratione voluptatem sequi nesciunt.","objects":{"entry":{"path":"src/pages/index.md","sha":"d7b93d697c0683382fdc21a159d749f562945dd0"},"files":[]},"timeStamp":"2019-09-06T18:35:16.305Z"}