{"type":"PR","pr":{"number":255,"head":"8e74317b6aa99788e5d85f2249e663ec45424ae2"},"user":"Sam","status":"pending_publish","branch":"cms/index","collection":"pages","title":"Hobbes","description":"Hobbes is team of ~~animators~~ problem solvers focused on furthering Motion as a design discipline and applying its principles to digital products and emerging technologies.","objects":{"entry":{"path":"src/pages/index.md","sha":"28c457e75da341d4d330a9869c9fcf246ae73e07"},"files":[]},"timeStamp":"2020-02-13T17:26:42.938Z"}